bimato/.DS_Store
bimato/__init__.py
bimato/api.py
bimato/core.py
bimato/network.py
bimato/poresize.py
bimato/utils.py
bimato-2022.2.1.dist-info/LICENSE
bimato-2022.2.1.dist-info/WHEEL
bimato-2022.2.1.dist-info/METADATA
bimato-2022.2.1.dist-info/RECORD
