Metadata-Version: 2.1
Name: bimato
Version: 2022.2.1
Summary: Bio Matrix Topology (BiMaTo) is a library containing all the biopolymer matrix topology analyses published by the Biological Physics Group, (BIP), Peter Debye Institute, University Leipzig, Germany.
Home-page: https://www.physgeo.uni-leipzig.de/en/pdi/biological-physics
License: GPL-3.0-or-later
Keywords: biophysics,biomaterials,poresize
Author: Tony Fischer (tku137)
Author-email: tonyfischer@mailbox.org
Requires-Python: >=3.8,<4.0
Classifier: License :: OSI Approved :: GNU General Public License v3 or later (GPLv3+)
Classifier: Programming Language :: Python :: 3
Classifier: Programming Language :: Python :: 3.8
Classifier: Programming Language :: Python :: 3.9
Classifier: Programming Language :: Python :: 3.10
Classifier: Programming Language :: Python :: 3.11
Requires-Dist: numpy (>=1.23.2,<2.0.0)
Requires-Dist: pandas (>=1.4.3,<2.0.0)
Requires-Dist: scikit-image (>=0.19.3,<0.20.0)
Requires-Dist: scipy (>=1.9.0,<2.0.0)
Project-URL: Documentation, https://bimato.readthedocs.io/
Project-URL: Repository, https://github.com/tku137/bimato
